seoman/__init__.py
seoman/__main__.py
seoman/auth.py
seoman/exceptions.py
seoman/main.py
seoman/service.py
seoman/utils/__init__.py
seoman/utils/completion_utils.py
seoman/utils/config_utils.py
seoman/utils/date_utils.py
seoman/utils/export_utils.py
seoman/utils/path_utils.py
seoman/utils/query_utils.py
seoman/utils/selector_utils.py
seoman/utils/service_utils.py
seoman_beta-1.1.0.dist-info/entry_points.txt
seoman_beta-1.1.0.dist-info/WHEEL
seoman_beta-1.1.0.dist-info/METADATA
seoman_beta-1.1.0.dist-info/RECORD
