Metadata-Version: 2.1
Name: seoman-beta
Version: 1.1.0
Summary: Beta version for seoman
Home-page: https://github.com/ycd/seoman-beta
License: GNU
Author: ycd
Author-email: yagizcanilbey1903@gmail.com
Requires-Python: >=3.6,<4.0
Classifier: License :: Other/Proprietary License
Classifier: Programming Language :: Python :: 3
Classifier: Programming Language :: Python :: 3.6
Classifier: Programming Language :: Python :: 3.7
Classifier: Programming Language :: Python :: 3.8
Classifier: Programming Language :: Python :: 3.9
Requires-Dist: google-api-python-client (>=1.10.1,<2.0.0)
Requires-Dist: google-auth-oauthlib (>=0.4.1,<0.5.0)
Requires-Dist: halo (>=0.0.30,<0.0.31)
Requires-Dist: inquirer (>=2.7.0,<3.0.0)
Requires-Dist: pyexcelerate (>=0.9.0,<0.10.0)
Requires-Dist: pytablewriter (>=0.58.0,<0.59.0)
Requires-Dist: requests (>=2.24.0,<3.0.0)
Requires-Dist: toml (>=0.10.1,<0.11.0)
Requires-Dist: typer (>=0.3.2,<0.4.0)
Project-URL: Repository, https://github.com/ycd/seoman-beta
